[
    {
        "id": 1,
        "name": "100gr",
        "description": "Bolsas de 100gr",
        "price":"$400",
        "category": "presentacion",
        "image": "100gr.jpg"
      },
      {
        "id": 2,
        "name": "250gr",
        "description": "Caja de 250gr",
        "price":"$1.000",
        "category": "presentacion",
        "image": "250gr.jpg"
      },
      {
        "id": 3,
        "name": "1kg",
        "description": "Caja de un kilo",
        "price":"$4.000",
        "category": "presentacion",
        "image": "1kg.jpg"
      }

]